yield2await.py
yield2await-0.0.1.dist-info/DESCRIPTION.rst
yield2await-0.0.1.dist-info/METADATA
yield2await-0.0.1.dist-info/RECORD
yield2await-0.0.1.dist-info/WHEEL
yield2await-0.0.1.dist-info/entry_points.txt
yield2await-0.0.1.dist-info/metadata.json
yield2await-0.0.1.dist-info/top_level.txt
