Metadata-Version: 2.0
Name: yield2await
Version: 0.0.1
Summary: Transform your python code to use async/await (PEP 492)
Home-page: https://github.com/alxpy/yield2await
Author: Oleksandr Kuzmenko
Author-email: UNKNOWN
License: MIT
Keywords: yield from asyncio coroutines with async await
Platform: UNKNOWN
Classifier: Development Status :: 3 - Alpha
Classifier: Intended Audience :: Developers
Classifier: License :: OSI Approved :: MIT License
Classifier: Programming Language :: Python :: 3
Classifier: Programming Language :: Python :: 3.5
Classifier: Programming Language :: Python :: 3.6
Requires-Python: >=3.5
Requires-Dist: astor (==0.6.2)
